BazingaBroServ/__init__.py
BazingaBroServ/service.py
bazingabro-0.1.0.dist-info/METADATA
bazingabro-0.1.0.dist-info/WHEEL
bazingabro-0.1.0.dist-info/entry_points.txt
bazingabro-0.1.0.dist-info/top_level.txt
bazingabro-0.1.0.dist-info/RECORD
