Metadata-Version: 2.4
Name: BazingaBro
Version: 0.1.0
Summary: An MCP server for integrating with X system.
Home-page: https://github.com/yourusername/BazingaBro
Author: Fahad Khan
Author-email: Fahad Khan <khan.fahad855@gmail.com>
License: MIT
Classifier: Programming Language :: Python :: 3.11
Classifier: License :: OSI Approved :: MIT License
Classifier: Operating System :: OS Independent
Classifier: Topic :: Scientific/Engineering :: Artificial Intelligence
Classifier: Framework :: FastAPI
Requires-Python: >=3.10
Requires-Dist: mcp
Dynamic: author
Dynamic: home-page
Dynamic: requires-python
